emsal/__init__.py
emsal/get_decisions.py
emsal-0.1.8.dist-info/LICENSE
emsal-0.1.8.dist-info/METADATA
emsal-0.1.8.dist-info/WHEEL
emsal-0.1.8.dist-info/top_level.txt
emsal-0.1.8.dist-info/RECORD
