Metadata-Version: 2.1
Name: emsal
Version: 0.1.8
Summary: A Python library that enables semi-automatic downloading of decisions based on year and decision number from the Supreme Court decision search interface.
Home-page: https://github.com/Bilirkisi/emsal
Author: Doğukan Arslan
Author-email: dogukan997@hotmail.com
License: UNKNOWN
Project-URL: Bug Tracker, https://github.com/Bilirkisi/emsal/issues
Platform: UNKNOWN
Classifier: Programming Language :: Python :: 3
Classifier: Development Status :: 5 - Production/Stable
Classifier: License :: OSI Approved :: GNU General Public License v3 or later (GPLv3+)
Classifier: Operating System :: OS Independent
Requires-Python: >=3.6
License-File: LICENSE
